LICENSE
MANIFEST.in
README.md
requirements.txt
setup.py
avro2py/VERSION
avro2py/__init__.py
avro2py/avro_types.py
avro2py/cli.py
avro2py/codegen.py
avro2py/rendering.py
avro2py/utils.py
avro2py.egg-info/PKG-INFO
avro2py.egg-info/SOURCES.txt
avro2py.egg-info/dependency_links.txt
avro2py.egg-info/entry_points.txt
avro2py.egg-info/requires.txt
avro2py.egg-info/top_level.txt