Metadata-Version: 2.1
Name: avro2py
Version: 0.0.7
Summary: Avro codegen for Python 3.6+
Home-page: https://github.com/hchasestevens/avro2py
Author: H. Chase Stevens
Author-email: chase@chasestevens.com
License: MIT
Platform: any
Classifier: Programming Language :: Python
Classifier: Programming Language :: Python :: 3
Classifier: Programming Language :: Python :: 3.6
Classifier: Topic :: Software Development :: Libraries :: Python Modules
Classifier: Intended Audience :: Developers
Classifier: Operating System :: OS Independent
Classifier: License :: OSI Approved :: MIT License
Provides-Extra: dev
